{
  "stage": 28,
  "mode": "enhanced rate model report",
  "stage26_csv": "/mnt/hdd2tC/haocheng/Mono-DFCGS/experiments/stage26_leave_one_out_full_video_rd/stage26_leave_one_out_full_video_rd.csv",
  "stage27_csv": "/mnt/hdd2tC/haocheng/Mono-DFCGS/experiments/stage27_anchor_available_selector_rd/stage27_anchor_available_selector_rd.csv",
  "bits": 8,
  "assumptions": {
    "anchor_payload": "q8 static anchor values only: 36864 Gaussians * 13 values * 8 bits per keyframe",
    "quant_params": "per-keyframe per-field min and scale stored as float32: 13 * 2 * 4 bytes",
    "indices": "uint16 frame index per keyframe",
    "timestamps": "uint16 timestamp per keyframe",
    "metadata": "fixed header 128 bytes + field table 64 bytes per video",
    "entropy": "zero-order entropy of q8 symbols after per-anchor uniform quantization; no entropy model/header overhead beyond metadata"
  },
  "csv": "/mnt/hdd2tC/haocheng/Mono-DFCGS/experiments/stage28_enhanced_rate_model_report/stage28_enhanced_rate_model_report.csv",
  "rows": [
    {
      "source_stage": "stage26",
      "sample": "n3dv",
      "method": "uniform",
      "reference_gap": 2,
      "total_frames": 81,
      "keyframe_count": 41,
      "indices": "0 2 4 6 8 10 12 14 16 18 20 22 24 26 28 30 32 34 36 38 40 42 44 46 48 50 52 54 56 58 60 62 64 66 68 70 72 74 76 78 80",
      "quality_adapter_all_psnr": 30.62798407101681,
      "quality_adapter_middle_psnr": 30.66295304628747,
      "primary_anchor_bytes": 19648512,
      "primary_anchor_mib_per_frame": 0.23133680555555555,
      "qparam_bytes": 4264,
      "index_bytes": 82,
      "timestamp_bytes": 82,
      "metadata_bytes": 192,
      "container_bytes": 19653132,
      "container_mib_per_frame": 0.2313912003128617,
      "container_overhead_bytes": 4620,
      "container_overhead_percent_vs_anchor": 0.023513230925578485,
      "entropy_anchor_bytes": 15653226,
      "entropy_anchor_mib_per_frame": 0.18429727907534,
      "entropy_container_bytes": 15657846,
      "entropy_container_mib_per_frame": 0.1843516738326461,
      "q8_zero_order_entropy_bits_per_value": 6.3732972756410255,
      "entropy_savings_percent_vs_raw_q8_anchor": 20.33378405448718
    },
    {
      "source_stage": "stage26",
      "sample": "n3dv",
      "method": "uniform",
      "reference_gap": 4,
      "total_frames": 81,
      "keyframe_count": 21,
      "indices": "0 4 8 12 16 20 24 28 32 36 40 44 48 52 56 60 64 68 72 76 80",
      "quality_adapter_all_psnr": 30.43016197026923,
      "quality_adapter_middle_psnr": 30.377133044209593,
      "primary_anchor_bytes": 10063872,
      "primary_anchor_mib_per_frame": 0.11848958333333333,
      "qparam_bytes": 2184,
      "index_bytes": 42,
      "timestamp_bytes": 42,
      "metadata_bytes": 192,
      "container_bytes": 10066332,
      "container_mib_per_frame": 0.1185185467755353,
      "container_overhead_bytes": 2460,
      "container_overhead_percent_vs_anchor": 0.0244438721001221,
      "entropy_anchor_bytes": 8017530,
      "entropy_anchor_mib_per_frame": 0.09439644990143953,
      "entropy_container_bytes": 8019990,
      "entropy_container_mib_per_frame": 0.09442541334364149,
      "q8_zero_order_entropy_bits_per_value": 6.373316353785103,
      "entropy_savings_percent_vs_raw_q8_anchor": 20.333545577686202
    },
    {
      "source_stage": "stage26",
      "sample": "n3dv",
      "method": "uniform",
      "reference_gap": 8,
      "total_frames": 81,
      "keyframe_count": 11,
      "indices": "0 8 16 24 32 40 48 56 64 72 80",
      "quality_adapter_all_psnr": 29.938864050082863,
      "quality_adapter_middle_psnr": 29.83762247304025,
      "primary_anchor_bytes": 5271552,
      "primary_anchor_mib_per_frame": 0.062065972222222224,
      "qparam_bytes": 1144,
      "index_bytes": 22,
      "timestamp_bytes": 22,
      "metadata_bytes": 192,
      "container_bytes": 5272932,
      "container_mib_per_frame": 0.06208222000687211,
      "container_overhead_bytes": 1380,
      "container_overhead_percent_vs_anchor": 0.026178248834498836,
      "entropy_anchor_bytes": 4199653,
      "entropy_anchor_mib_per_frame": 0.0494456938755365,
      "entropy_container_bytes": 4201033,
      "entropy_container_mib_per_frame": 0.049461941660186394,
      "q8_zero_order_entropy_bits_per_value": 6.373307898698524,
      "entropy_savings_percent_vs_raw_q8_anchor": 20.333651266268454
    },
    {
      "source_stage": "stage26",
      "sample": "n3dv",
      "method": "uniform",
      "reference_gap": 16,
      "total_frames": 81,
      "keyframe_count": 6,
      "indices": "0 16 32 48 64 80",
      "quality_adapter_all_psnr": 29.126479340846256,
      "quality_adapter_middle_psnr": 29.010518457525517,
      "primary_anchor_bytes": 2875392,
      "primary_anchor_mib_per_frame": 0.033854166666666664,
      "qparam_bytes": 624,
      "index_bytes": 12,
      "timestamp_bytes": 12,
      "metadata_bytes": 192,
      "container_bytes": 2876232,
      "container_mib_per_frame": 0.03386405662254051,
      "container_overhead_bytes": 840,
      "container_overhead_percent_vs_anchor": 0.02921340811965812,
      "entropy_anchor_bytes": 2290706,
      "entropy_anchor_mib_per_frame": 0.02697021578565056,
      "entropy_container_bytes": 2291546,
      "entropy_container_mib_per_frame": 0.0269801057415244,
      "q8_zero_order_entropy_bits_per_value": 6.373269453347579,
      "entropy_savings_percent_vs_raw_q8_anchor": 20.334131833155272
    },
    {
      "source_stage": "stage26",
      "sample": "meetroom",
      "method": "uniform",
      "reference_gap": 2,
      "total_frames": 81,
      "keyframe_count": 41,
      "indices": "0 2 4 6 8 10 12 14 16 18 20 22 24 26 28 30 32 34 36 38 40 42 44 46 48 50 52 54 56 58 60 62 64 66 68 70 72 74 76 78 80",
      "quality_adapter_all_psnr": 30.894844910411546,
      "quality_adapter_middle_psnr": 30.28400074101079,
      "primary_anchor_bytes": 19648512,
      "primary_anchor_mib_per_frame": 0.23133680555555555,
      "qparam_bytes": 4264,
      "index_bytes": 82,
      "timestamp_bytes": 82,
      "metadata_bytes": 192,
      "container_bytes": 19653132,
      "container_mib_per_frame": 0.2313912003128617,
      "container_overhead_bytes": 4620,
      "container_overhead_percent_vs_anchor": 0.023513230925578485,
      "entropy_anchor_bytes": 15620062,
      "entropy_anchor_mib_per_frame": 0.18390681419843508,
      "entropy_container_bytes": 15624682,
      "entropy_container_mib_per_frame": 0.18396120895574122,
      "q8_zero_order_entropy_bits_per_value": 6.359794370179278,
      "entropy_savings_percent_vs_raw_q8_anchor": 20.502570372759017
    },
    {
      "source_stage": "stage26",
      "sample": "meetroom",
      "method": "uniform",
      "reference_gap": 4,
      "total_frames": 81,
      "keyframe_count": 21,
      "indices": "0 4 8 12 16 20 24 28 32 36 40 44 48 52 56 60 64 68 72 76 80",
      "quality_adapter_all_psnr": 29.643361488861682,
      "quality_adapter_middle_psnr": 29.007922638839677,
      "primary_anchor_bytes": 10063872,
      "primary_anchor_mib_per_frame": 0.11848958333333333,
      "qparam_bytes": 2184,
      "index_bytes": 42,
      "timestamp_bytes": 42,
      "metadata_bytes": 192,
      "container_bytes": 10066332,
      "container_mib_per_frame": 0.1185185467755353,
      "container_overhead_bytes": 2460,
      "container_overhead_percent_vs_anchor": 0.0244438721001221,
      "entropy_anchor_bytes": 8001166,
      "entropy_anchor_mib_per_frame": 0.09420378414201147,
      "entropy_container_bytes": 8003626,
      "entropy_container_mib_per_frame": 0.09423274758421345,
      "q8_zero_order_entropy_bits_per_value": 6.360308239214489,
      "entropy_savings_percent_vs_raw_q8_anchor": 20.496147009818884
    },
    {
      "source_stage": "stage26",
      "sample": "meetroom",
      "method": "uniform",
      "reference_gap": 8,
      "total_frames": 81,
      "keyframe_count": 11,
      "indices": "0 8 16 24 32 40 48 56 64 72 80",
      "quality_adapter_all_psnr": 27.920306664848763,
      "quality_adapter_middle_psnr": 27.36305183891128,
      "primary_anchor_bytes": 5271552,
      "primary_anchor_mib_per_frame": 0.062065972222222224,
      "qparam_bytes": 1144,
      "index_bytes": 22,
      "timestamp_bytes": 22,
      "metadata_bytes": 192,
      "container_bytes": 5272932,
      "container_mib_per_frame": 0.06208222000687211,
      "container_overhead_bytes": 1380,
      "container_overhead_percent_vs_anchor": 0.026178248834498836,
      "entropy_anchor_bytes": 4191367,
      "entropy_anchor_mib_per_frame": 0.049348136525095246,
      "entropy_container_bytes": 4192747,
      "entropy_container_mib_per_frame": 0.04936438430974513,
      "q8_zero_order_entropy_bits_per_value": 6.360733233780109,
      "entropy_savings_percent_vs_raw_q8_anchor": 20.49083457774864
    },
    {
      "source_stage": "stage26",
      "sample": "meetroom",
      "method": "uniform",
      "reference_gap": 16,
      "total_frames": 81,
      "keyframe_count": 6,
      "indices": "0 16 32 48 64 80",
      "quality_adapter_all_psnr": 25.992687296753708,
      "quality_adapter_middle_psnr": 25.5550354595181,
      "primary_anchor_bytes": 2875392,
      "primary_anchor_mib_per_frame": 0.033854166666666664,
      "qparam_bytes": 624,
      "index_bytes": 12,
      "timestamp_bytes": 12,
      "metadata_bytes": 192,
      "container_bytes": 2876232,
      "container_mib_per_frame": 0.03386405662254051,
      "container_overhead_bytes": 840,
      "container_overhead_percent_vs_anchor": 0.02921340811965812,
      "entropy_anchor_bytes": 2286379,
      "entropy_anchor_mib_per_frame": 0.026919270739143276,
      "entropy_container_bytes": 2287219,
      "entropy_container_mib_per_frame": 0.02692916069501712,
      "q8_zero_order_entropy_bits_per_value": 6.361230746972934,
      "entropy_savings_percent_vs_raw_q8_anchor": 20.48461566283832
    },
    {
      "source_stage": "stage26",
      "sample": "driving",
      "method": "uniform",
      "reference_gap": 2,
      "total_frames": 81,
      "keyframe_count": 41,
      "indices": "0 2 4 6 8 10 12 14 16 18 20 22 24 26 28 30 32 34 36 38 40 42 44 46 48 50 52 54 56 58 60 62 64 66 68 70 72 74 76 78 80",
      "quality_adapter_all_psnr": 30.284167575815744,
      "quality_adapter_middle_psnr": 28.0512502810251,
      "primary_anchor_bytes": 19648512,
      "primary_anchor_mib_per_frame": 0.23133680555555555,
      "qparam_bytes": 4264,
      "index_bytes": 82,
      "timestamp_bytes": 82,
      "metadata_bytes": 192,
      "container_bytes": 19653132,
      "container_mib_per_frame": 0.2313912003128617,
      "container_overhead_bytes": 4620,
      "container_overhead_percent_vs_anchor": 0.023513230925578485,
      "entropy_anchor_bytes": 15456070,
      "entropy_anchor_mib_per_frame": 0.18197601224169319,
      "entropy_container_bytes": 15460690,
      "entropy_container_mib_per_frame": 0.18203040699899933,
      "q8_zero_order_entropy_bits_per_value": 6.293024123149885,
      "entropy_savings_percent_vs_raw_q8_anchor": 21.337198460626432
    },
    {
      "source_stage": "stage26",
      "sample": "driving",
      "method": "uniform",
      "reference_gap": 4,
      "total_frames": 81,
      "keyframe_count": 21,
      "indices": "0 4 8 12 16 20 24 28 32 36 40 44 48 52 56 60 64 68 72 76 80",
      "quality_adapter_all_psnr": 27.987380242575348,
      "quality_adapter_middle_psnr": 26.4305304447841,
      "primary_anchor_bytes": 10063872,
      "primary_anchor_mib_per_frame": 0.11848958333333333,
      "qparam_bytes": 2184,
      "index_bytes": 42,
      "timestamp_bytes": 42,
      "metadata_bytes": 192,
      "container_bytes": 10066332,
      "container_mib_per_frame": 0.1185185467755353,
      "container_overhead_bytes": 2460,
      "container_overhead_percent_vs_anchor": 0.0244438721001221,
      "entropy_anchor_bytes": 7917830,
      "entropy_anchor_mib_per_frame": 0.09322260632927035,
      "entropy_container_bytes": 7920290,
      "entropy_container_mib_per_frame": 0.09325156977147232,
      "q8_zero_order_entropy_bits_per_value": 6.294062563593814,
      "entropy_savings_percent_vs_raw_q8_anchor": 21.32421795507733
    },
    {
      "source_stage": "stage26",
      "sample": "driving",
      "method": "uniform",
      "reference_gap": 8,
      "total_frames": 81,
      "keyframe_count": 11,
      "indices": "0 8 16 24 32 40 48 56 64 72 80",
      "quality_adapter_all_psnr": 25.776327977130347,
      "quality_adapter_middle_psnr": 24.73501005518895,
      "primary_anchor_bytes": 5271552,
      "primary_anchor_mib_per_frame": 0.062065972222222224,
      "qparam_bytes": 1144,
      "index_bytes": 22,
      "timestamp_bytes": 22,
      "metadata_bytes": 192,
      "container_bytes": 5272932,
      "container_mib_per_frame": 0.06208222000687211,
      "container_overhead_bytes": 1380,
      "container_overhead_percent_vs_anchor": 0.026178248834498836,
      "entropy_anchor_bytes": 4148511,
      "entropy_anchor_mib_per_frame": 0.04884356039541739,
      "entropy_container_bytes": 4149891,
      "entropy_container_mib_per_frame": 0.04885980818006727,
      "q8_zero_order_entropy_bits_per_value": 6.295695840617715,
      "entropy_savings_percent_vs_raw_q8_anchor": 21.303801992278554
    },
    {
      "source_stage": "stage26",
      "sample": "driving",
      "method": "uniform",
      "reference_gap": 16,
      "total_frames": 81,
      "keyframe_count": 6,
      "indices": "0 16 32 48 64 80",
      "quality_adapter_all_psnr": 23.80466315736545,
      "quality_adapter_middle_psnr": 23.118391485295174,
      "primary_anchor_bytes": 2875392,
      "primary_anchor_mib_per_frame": 0.033854166666666664,
      "qparam_bytes": 624,
      "index_bytes": 12,
      "timestamp_bytes": 12,
      "metadata_bytes": 192,
      "container_bytes": 2876232,
      "container_mib_per_frame": 0.03386405662254051,
      "container_overhead_bytes": 840,
      "container_overhead_percent_vs_anchor": 0.02921340811965812,
      "entropy_anchor_bytes": 2263506,
      "entropy_anchor_mib_per_frame": 0.026649969595449942,
      "entropy_container_bytes": 2264346,
      "entropy_container_mib_per_frame": 0.026659859551323786,
      "q8_zero_order_entropy_bits_per_value": 6.29759281517094,
      "entropy_savings_percent_vs_raw_q8_anchor": 21.280089810363247
    },
    {
      "source_stage": "stage26",
      "sample": "robot",
      "method": "uniform",
      "reference_gap": 2,
      "total_frames": 77,
      "keyframe_count": 39,
      "indices": "0 2 4 6 8 10 12 14 16 18 20 22 24 26 28 30 32 34 36 38 40 42 44 46 48 50 52 54 56 58 60 62 64 66 68 70 72 74 76",
      "quality_adapter_all_psnr": 27.959097139933412,
      "quality_adapter_middle_psnr": 24.01326212410277,
      "primary_anchor_bytes": 18690048,
      "primary_anchor_mib_per_frame": 0.2314833603896104,
      "qparam_bytes": 4056,
      "index_bytes": 78,
      "timestamp_bytes": 78,
      "metadata_bytes": 192,
      "container_bytes": 18694452,
      "container_mib_per_frame": 0.23153790560635654,
      "container_overhead_bytes": 4404,
      "container_overhead_percent_vs_anchor": 0.023563342373438528,
      "entropy_anchor_bytes": 14893053,
      "entropy_anchor_mib_per_frame": 0.18445613167502664,
      "entropy_container_bytes": 14897457,
      "entropy_container_mib_per_frame": 0.18451067689177278,
      "q8_zero_order_entropy_bits_per_value": 6.374752167570677,
      "entropy_savings_percent_vs_raw_q8_anchor": 20.315597905366534
    },
    {
      "source_stage": "stage26",
      "sample": "robot",
      "method": "uniform",
      "reference_gap": 4,
      "total_frames": 77,
      "keyframe_count": 20,
      "indices": "0 4 8 12 16 20 24 28 32 36 40 44 48 52 56 60 64 68 72 76",
      "quality_adapter_all_psnr": 25.191348180558062,
      "quality_adapter_middle_psnr": 22.874259284410844,
      "primary_anchor_bytes": 9584640,
      "primary_anchor_mib_per_frame": 0.11870941558441558,
      "qparam_bytes": 2080,
      "index_bytes": 40,
      "timestamp_bytes": 40,
      "metadata_bytes": 192,
      "container_bytes": 9586992,
      "container_mib_per_frame": 0.11873854599989854,
      "container_overhead_bytes": 2352,
      "container_overhead_percent_vs_anchor": 0.02453926282051282,
      "entropy_anchor_bytes": 7637314,
      "entropy_anchor_mib_per_frame": 0.09459104166402445,
      "entropy_container_bytes": 7639666,
      "entropy_container_mib_per_frame": 0.0946201720795074,
      "q8_zero_order_entropy_bits_per_value": 6.374627737713675,
      "entropy_savings_percent_vs_raw_q8_anchor": 20.31715327857906
    },
    {
      "source_stage": "stage26",
      "sample": "robot",
      "method": "uniform",
      "reference_gap": 8,
      "total_frames": 77,
      "keyframe_count": 11,
      "indices": "0 8 16 24 32 40 48 56 64 72 76",
      "quality_adapter_all_psnr": 22.98304243524862,
      "quality_adapter_middle_psnr": 21.5125972296323,
      "primary_anchor_bytes": 5271552,
      "primary_anchor_mib_per_frame": 0.06529017857142858,
      "qparam_bytes": 1144,
      "index_bytes": 22,
      "timestamp_bytes": 22,
      "metadata_bytes": 192,
      "container_bytes": 5272932,
      "container_mib_per_frame": 0.06530727039683949,
      "container_overhead_bytes": 1380,
      "container_overhead_percent_vs_anchor": 0.026178248834498836,
      "entropy_anchor_bytes": 4200969,
      "entropy_anchor_mib_per_frame": 0.052030600510634385,
      "entropy_container_bytes": 4202349,
      "entropy_container_mib_per_frame": 0.0520476923360453,
      "q8_zero_order_entropy_bits_per_value": 6.375305033508159,
      "entropy_savings_percent_vs_raw_q8_anchor": 20.30868708114802
    },
    {
      "source_stage": "stage26",
      "sample": "robot",
      "method": "uniform",
      "reference_gap": 16,
      "total_frames": 77,
      "keyframe_count": 6,
      "indices": "0 16 32 48 64 76",
      "quality_adapter_all_psnr": 21.426327081480736,
      "quality_adapter_middle_psnr": 20.554419459079334,
      "primary_anchor_bytes": 2875392,
      "primary_anchor_mib_per_frame": 0.03561282467532467,
      "qparam_bytes": 624,
      "index_bytes": 12,
      "timestamp_bytes": 12,
      "metadata_bytes": 192,
      "container_bytes": 2876232,
      "container_mib_per_frame": 0.03562322839514002,
      "container_overhead_bytes": 840,
      "container_overhead_percent_vs_anchor": 0.02921340811965812,
      "entropy_anchor_bytes": 2291764,
      "entropy_anchor_mib_per_frame": 0.02838436968914874,
      "entropy_container_bytes": 2292604,
      "entropy_container_mib_per_frame": 0.028394773408964083,
      "q8_zero_order_entropy_bits_per_value": 6.376213051994302,
      "entropy_savings_percent_vs_raw_q8_anchor": 20.297336850071225
    },
    {
      "source_stage": "stage27",
      "sample": "n3dv",
      "method": "uniform",
      "reference_gap": 4,
      "total_frames": 81,
      "keyframe_count": 21,
      "indices": "0 4 8 12 16 20 24 28 32 36 40 44 48 52 56 60 64 68 72 76 80",
      "quality_adapter_all_psnr": 30.42995205593874,
      "quality_adapter_middle_psnr": 30.377245431774345,
      "primary_anchor_bytes": 10063872,
      "primary_anchor_mib_per_frame": 0.11848958333333333,
      "qparam_bytes": 2184,
      "index_bytes": 42,
      "timestamp_bytes": 42,
      "metadata_bytes": 192,
      "container_bytes": 10066332,
      "container_mib_per_frame": 0.1185185467755353,
      "container_overhead_bytes": 2460,
      "container_overhead_percent_vs_anchor": 0.0244438721001221,
      "entropy_anchor_bytes": 8017530,
      "entropy_anchor_mib_per_frame": 0.09439644990143953,
      "entropy_container_bytes": 8019990,
      "entropy_container_mib_per_frame": 0.09442541334364149,
      "q8_zero_order_entropy_bits_per_value": 6.373316353785103,
      "entropy_savings_percent_vs_raw_q8_anchor": 20.333545577686202
    },
    {
      "source_stage": "stage27",
      "sample": "n3dv",
      "method": "anchor_segment_rd",
      "reference_gap": 4,
      "total_frames": 81,
      "keyframe_count": 21,
      "indices": "0 2 4 6 10 16 20 26 30 36 40 44 46 50 54 60 64 70 72 76 80",
      "quality_adapter_all_psnr": 30.437727068324932,
      "quality_adapter_middle_psnr": 30.38496844484929,
      "primary_anchor_bytes": 10063872,
      "primary_anchor_mib_per_frame": 0.11848958333333333,
      "qparam_bytes": 2184,
      "index_bytes": 42,
      "timestamp_bytes": 42,
      "metadata_bytes": 192,
      "container_bytes": 10066332,
      "container_mib_per_frame": 0.1185185467755353,
      "container_overhead_bytes": 2460,
      "container_overhead_percent_vs_anchor": 0.0244438721001221,
      "entropy_anchor_bytes": 8017317,
      "entropy_anchor_mib_per_frame": 0.09439394209120008,
      "entropy_container_bytes": 8019777,
      "entropy_container_mib_per_frame": 0.09442290553340206,
      "q8_zero_order_entropy_bits_per_value": 6.373147035256411,
      "entropy_savings_percent_vs_raw_q8_anchor": 20.335662059294872
    },
    {
      "source_stage": "stage27",
      "sample": "n3dv",
      "method": "uniform",
      "reference_gap": 8,
      "total_frames": 81,
      "keyframe_count": 11,
      "indices": "0 8 16 24 32 40 48 56 64 72 80",
      "quality_adapter_all_psnr": 29.937633845392252,
      "quality_adapter_middle_psnr": 29.836435588688385,
      "primary_anchor_bytes": 5271552,
      "primary_anchor_mib_per_frame": 0.062065972222222224,
      "qparam_bytes": 1144,
      "index_bytes": 22,
      "timestamp_bytes": 22,
      "metadata_bytes": 192,
      "container_bytes": 5272932,
      "container_mib_per_frame": 0.06208222000687211,
      "container_overhead_bytes": 1380,
      "container_overhead_percent_vs_anchor": 0.026178248834498836,
      "entropy_anchor_bytes": 4199653,
      "entropy_anchor_mib_per_frame": 0.0494456938755365,
      "entropy_container_bytes": 4201033,
      "entropy_container_mib_per_frame": 0.049461941660186394,
      "q8_zero_order_entropy_bits_per_value": 6.373307898698524,
      "entropy_savings_percent_vs_raw_q8_anchor": 20.333651266268454
    },
    {
      "source_stage": "stage27",
      "sample": "n3dv",
      "method": "anchor_segment_rd",
      "reference_gap": 8,
      "total_frames": 81,
      "keyframe_count": 11,
      "indices": "0 2 6 12 20 32 40 50 60 70 80",
      "quality_adapter_all_psnr": 29.943094831897145,
      "quality_adapter_middle_psnr": 29.84209256470866,
      "primary_anchor_bytes": 5271552,
      "primary_anchor_mib_per_frame": 0.062065972222222224,
      "qparam_bytes": 1144,
      "index_bytes": 22,
      "timestamp_bytes": 22,
      "metadata_bytes": 192,
      "container_bytes": 5272932,
      "container_mib_per_frame": 0.06208222000687211,
      "container_overhead_bytes": 1380,
      "container_overhead_percent_vs_anchor": 0.026178248834498836,
      "entropy_anchor_bytes": 4199525,
      "entropy_anchor_mib_per_frame": 0.04944418683464145,
      "entropy_container_bytes": 4200905,
      "entropy_container_mib_per_frame": 0.04946043461929133,
      "q8_zero_order_entropy_bits_per_value": 6.373113648504273,
      "entropy_savings_percent_vs_raw_q8_anchor": 20.336079393696583
    },
    {
      "source_stage": "stage27",
      "sample": "n3dv",
      "method": "uniform",
      "reference_gap": 16,
      "total_frames": 81,
      "keyframe_count": 6,
      "indices": "0 16 32 48 64 80",
      "quality_adapter_all_psnr": 29.123841344034442,
      "quality_adapter_middle_psnr": 29.00794376712806,
      "primary_anchor_bytes": 2875392,
      "primary_anchor_mib_per_frame": 0.033854166666666664,
      "qparam_bytes": 624,
      "index_bytes": 12,
      "timestamp_bytes": 12,
      "metadata_bytes": 192,
      "container_bytes": 2876232,
      "container_mib_per_frame": 0.03386405662254051,
      "container_overhead_bytes": 840,
      "container_overhead_percent_vs_anchor": 0.02921340811965812,
      "entropy_anchor_bytes": 2290706,
      "entropy_anchor_mib_per_frame": 0.02697021578565056,
      "entropy_container_bytes": 2291546,
      "entropy_container_mib_per_frame": 0.0269801057415244,
      "q8_zero_order_entropy_bits_per_value": 6.373269453347579,
      "entropy_savings_percent_vs_raw_q8_anchor": 20.334131833155272
    },
    {
      "source_stage": "stage27",
      "sample": "n3dv",
      "method": "anchor_segment_rd",
      "reference_gap": 16,
      "total_frames": 81,
      "keyframe_count": 6,
      "indices": "0 6 14 40 60 80",
      "quality_adapter_all_psnr": 29.278378243735816,
      "quality_adapter_middle_psnr": 29.174061694539894,
      "primary_anchor_bytes": 2875392,
      "primary_anchor_mib_per_frame": 0.033854166666666664,
      "qparam_bytes": 624,
      "index_bytes": 12,
      "timestamp_bytes": 12,
      "metadata_bytes": 192,
      "container_bytes": 2876232,
      "container_mib_per_frame": 0.03386405662254051,
      "container_overhead_bytes": 840,
      "container_overhead_percent_vs_anchor": 0.02921340811965812,
      "entropy_anchor_bytes": 2290684,
      "entropy_anchor_mib_per_frame": 0.02696995676299672,
      "entropy_container_bytes": 2291524,
      "entropy_container_mib_per_frame": 0.026979846718870562,
      "q8_zero_order_entropy_bits_per_value": 6.373208244301995,
      "entropy_savings_percent_vs_raw_q8_anchor": 20.334896946225072
    },
    {
      "source_stage": "stage27",
      "sample": "meetroom",
      "method": "uniform",
      "reference_gap": 4,
      "total_frames": 81,
      "keyframe_count": 21,
      "indices": "0 4 8 12 16 20 24 28 32 36 40 44 48 52 56 60 64 68 72 76 80",
      "quality_adapter_all_psnr": 29.6434932695428,
      "quality_adapter_middle_psnr": 29.00801329678916,
      "primary_anchor_bytes": 10063872,
      "primary_anchor_mib_per_frame": 0.11848958333333333,
      "qparam_bytes": 2184,
      "index_bytes": 42,
      "timestamp_bytes": 42,
      "metadata_bytes": 192,
      "container_bytes": 10066332,
      "container_mib_per_frame": 0.1185185467755353,
      "container_overhead_bytes": 2460,
      "container_overhead_percent_vs_anchor": 0.0244438721001221,
      "entropy_anchor_bytes": 8001166,
      "entropy_anchor_mib_per_frame": 0.09420378414201147,
      "entropy_container_bytes": 8003626,
      "entropy_container_mib_per_frame": 0.09423274758421345,
      "q8_zero_order_entropy_bits_per_value": 6.360308239214489,
      "entropy_savings_percent_vs_raw_q8_anchor": 20.496147009818884
    },
    {
      "source_stage": "stage27",
      "sample": "meetroom",
      "method": "anchor_segment_rd",
      "reference_gap": 4,
      "total_frames": 81,
      "keyframe_count": 21,
      "indices": "0 4 6 10 16 20 24 26 30 36 40 44 50 56 60 62 64 66 70 74 80",
      "quality_adapter_all_psnr": 29.53204311929575,
      "quality_adapter_middle_psnr": 28.849059601907104,
      "primary_anchor_bytes": 10063872,
      "primary_anchor_mib_per_frame": 0.11848958333333333,
      "qparam_bytes": 2184,
      "index_bytes": 42,
      "timestamp_bytes": 42,
      "metadata_bytes": 192,
      "container_bytes": 10066332,
      "container_mib_per_frame": 0.1185185467755353,
      "container_overhead_bytes": 2460,
      "container_overhead_percent_vs_anchor": 0.0244438721001221,
      "entropy_anchor_bytes": 8001256,
      "entropy_anchor_mib_per_frame": 0.09420484378014082,
      "entropy_container_bytes": 8003716,
      "entropy_container_mib_per_frame": 0.09423380722234279,
      "q8_zero_order_entropy_bits_per_value": 6.360379782254782,
      "entropy_savings_percent_vs_raw_q8_anchor": 20.495252721815223
    },
    {
      "source_stage": "stage27",
      "sample": "meetroom",
      "method": "uniform",
      "reference_gap": 8,
      "total_frames": 81,
      "keyframe_count": 11,
      "indices": "0 8 16 24 32 40 48 56 64 72 80",
      "quality_adapter_all_psnr": 27.920439244388305,
      "quality_adapter_middle_psnr": 27.363162509177375,
      "primary_anchor_bytes": 5271552,
      "primary_anchor_mib_per_frame": 0.062065972222222224,
      "qparam_bytes": 1144,
      "index_bytes": 22,
      "timestamp_bytes": 22,
      "metadata_bytes": 192,
      "container_bytes": 5272932,
      "container_mib_per_frame": 0.06208222000687211,
      "container_overhead_bytes": 1380,
      "container_overhead_percent_vs_anchor": 0.026178248834498836,
      "entropy_anchor_bytes": 4191367,
      "entropy_anchor_mib_per_frame": 0.049348136525095246,
      "entropy_container_bytes": 4192747,
      "entropy_container_mib_per_frame": 0.04936438430974513,
      "q8_zero_order_entropy_bits_per_value": 6.360733233780109,
      "entropy_savings_percent_vs_raw_q8_anchor": 20.49083457774864
    },
    {
      "source_stage": "stage27",
      "sample": "meetroom",
      "method": "anchor_segment_rd",
      "reference_gap": 8,
      "total_frames": 81,
      "keyframe_count": 11,
      "indices": "0 10 20 28 40 44 52 60 64 68 80",
      "quality_adapter_all_psnr": 27.626549369075246,
      "quality_adapter_middle_psnr": 27.021988134970304,
      "primary_anchor_bytes": 5271552,
      "primary_anchor_mib_per_frame": 0.062065972222222224,
      "qparam_bytes": 1144,
      "index_bytes": 22,
      "timestamp_bytes": 22,
      "metadata_bytes": 192,
      "container_bytes": 5272932,
      "container_mib_per_frame": 0.06208222000687211,
      "container_overhead_bytes": 1380,
      "container_overhead_percent_vs_anchor": 0.026178248834498836,
      "entropy_anchor_bytes": 4191463,
      "entropy_anchor_mib_per_frame": 0.04934926680576654,
      "entropy_container_bytes": 4192843,
      "entropy_container_mib_per_frame": 0.04936551459041642,
      "q8_zero_order_entropy_bits_per_value": 6.360878921425797,
      "entropy_savings_percent_vs_raw_q8_anchor": 20.489013482177544
    },
    {
      "source_stage": "stage27",
      "sample": "meetroom",
      "method": "uniform",
      "reference_gap": 16,
      "total_frames": 81,
      "keyframe_count": 6,
      "indices": "0 16 32 48 64 80",
      "quality_adapter_all_psnr": 25.99323726745736,
      "quality_adapter_middle_psnr": 25.555626219259906,
      "primary_anchor_bytes": 2875392,
      "primary_anchor_mib_per_frame": 0.033854166666666664,
      "qparam_bytes": 624,
      "index_bytes": 12,
      "timestamp_bytes": 12,
      "metadata_bytes": 192,
      "container_bytes": 2876232,
      "container_mib_per_frame": 0.03386405662254051,
      "container_overhead_bytes": 840,
      "container_overhead_percent_vs_anchor": 0.02921340811965812,
      "entropy_anchor_bytes": 2286379,
      "entropy_anchor_mib_per_frame": 0.026919270739143276,
      "entropy_container_bytes": 2287219,
      "entropy_container_mib_per_frame": 0.02692916069501712,
      "q8_zero_order_entropy_bits_per_value": 6.361230746972934,
      "entropy_savings_percent_vs_raw_q8_anchor": 20.48461566283832
    },
    {
      "source_stage": "stage27",
      "sample": "meetroom",
      "method": "anchor_segment_rd",
      "reference_gap": 16,
      "total_frames": 81,
      "keyframe_count": 6,
      "indices": "0 20 40 60 68 80",
      "quality_adapter_all_psnr": 25.54101572650186,
      "quality_adapter_middle_psnr": 25.067160614522177,
      "primary_anchor_bytes": 2875392,
      "primary_anchor_mib_per_frame": 0.033854166666666664,
      "qparam_bytes": 624,
      "index_bytes": 12,
      "timestamp_bytes": 12,
      "metadata_bytes": 192,
      "container_bytes": 2876232,
      "container_mib_per_frame": 0.03386405662254051,
      "container_overhead_bytes": 840,
      "container_overhead_percent_vs_anchor": 0.02921340811965812,
      "entropy_anchor_bytes": 2286525,
      "entropy_anchor_mib_per_frame": 0.026920989707664208,
      "entropy_container_bytes": 2287365,
      "entropy_container_mib_per_frame": 0.02693087966353805,
      "q8_zero_order_entropy_bits_per_value": 6.361636952457265,
      "entropy_savings_percent_vs_raw_q8_anchor": 20.479538094284187
    },
    {
      "source_stage": "stage27",
      "sample": "driving",
      "method": "uniform",
      "reference_gap": 4,
      "total_frames": 81,
      "keyframe_count": 21,
      "indices": "0 4 8 12 16 20 24 28 32 36 40 44 48 52 56 60 64 68 72 76 80",
      "quality_adapter_all_psnr": 27.987381263755843,
      "quality_adapter_middle_psnr": 26.430545656168047,
      "primary_anchor_bytes": 10063872,
      "primary_anchor_mib_per_frame": 0.11848958333333333,
      "qparam_bytes": 2184,
      "index_bytes": 42,
      "timestamp_bytes": 42,
      "metadata_bytes": 192,
      "container_bytes": 10066332,
      "container_mib_per_frame": 0.1185185467755353,
      "container_overhead_bytes": 2460,
      "container_overhead_percent_vs_anchor": 0.0244438721001221,
      "entropy_anchor_bytes": 7917830,
      "entropy_anchor_mib_per_frame": 0.09322260632927035,
      "entropy_container_bytes": 7920290,
      "entropy_container_mib_per_frame": 0.09325156977147232,
      "q8_zero_order_entropy_bits_per_value": 6.294062563593814,
      "entropy_savings_percent_vs_raw_q8_anchor": 21.32421795507733
    },
    {
      "source_stage": "stage27",
      "sample": "driving",
      "method": "anchor_segment_rd",
      "reference_gap": 4,
      "total_frames": 81,
      "keyframe_count": 21,
      "indices": "0 2 4 6 8 10 12 14 18 22 28 34 38 42 48 54 58 64 70 76 80",
      "quality_adapter_all_psnr": 27.83541066050171,
      "quality_adapter_middle_psnr": 26.210277751963407,
      "primary_anchor_bytes": 10063872,
      "primary_anchor_mib_per_frame": 0.11848958333333333,
      "qparam_bytes": 2184,
      "index_bytes": 42,
      "timestamp_bytes": 42,
      "metadata_bytes": 192,
      "container_bytes": 10066332,
      "container_mib_per_frame": 0.1185185467755353,
      "container_overhead_bytes": 2460,
      "container_overhead_percent_vs_anchor": 0.0244438721001221,
      "entropy_anchor_bytes": 7920496,
      "entropy_anchor_mib_per_frame": 0.09325399516541281,
      "entropy_container_bytes": 7922956,
      "entropy_container_mib_per_frame": 0.09328295860761478,
      "q8_zero_order_entropy_bits_per_value": 6.296181827431828,
      "entropy_savings_percent_vs_raw_q8_anchor": 21.297727157102155
    },
    {
      "source_stage": "stage27",
      "sample": "driving",
      "method": "uniform",
      "reference_gap": 8,
      "total_frames": 81,
      "keyframe_count": 11,
      "indices": "0 8 16 24 32 40 48 56 64 72 80",
      "quality_adapter_all_psnr": 25.77631998434536,
      "quality_adapter_middle_psnr": 24.73502457743958,
      "primary_anchor_bytes": 5271552,
      "primary_anchor_mib_per_frame": 0.062065972222222224,
      "qparam_bytes": 1144,
      "index_bytes": 22,
      "timestamp_bytes": 22,
      "metadata_bytes": 192,
      "container_bytes": 5272932,
      "container_mib_per_frame": 0.06208222000687211,
      "container_overhead_bytes": 1380,
      "container_overhead_percent_vs_anchor": 0.026178248834498836,
      "entropy_anchor_bytes": 4148511,
      "entropy_anchor_mib_per_frame": 0.04884356039541739,
      "entropy_container_bytes": 4149891,
      "entropy_container_mib_per_frame": 0.04885980818006727,
      "q8_zero_order_entropy_bits_per_value": 6.295695840617715,
      "entropy_savings_percent_vs_raw_q8_anchor": 21.303801992278554
    },
    {
      "source_stage": "stage27",
      "sample": "driving",
      "method": "anchor_segment_rd",
      "reference_gap": 8,
      "total_frames": 81,
      "keyframe_count": 11,
      "indices": "0 4 8 12 18 28 38 46 58 70 80",
      "quality_adapter_all_psnr": 25.596039555553578,
      "quality_adapter_middle_psnr": 24.513809729447093,
      "primary_anchor_bytes": 5271552,
      "primary_anchor_mib_per_frame": 0.062065972222222224,
      "qparam_bytes": 1144,
      "index_bytes": 22,
      "timestamp_bytes": 22,
      "metadata_bytes": 192,
      "container_bytes": 5272932,
      "container_mib_per_frame": 0.06208222000687211,
      "container_overhead_bytes": 1380,
      "container_overhead_percent_vs_anchor": 0.026178248834498836,
      "entropy_anchor_bytes": 4149115,
      "entropy_anchor_mib_per_frame": 0.048850671744640965,
      "entropy_container_bytes": 4150495,
      "entropy_container_mib_per_frame": 0.04886691952929085,
      "q8_zero_order_entropy_bits_per_value": 6.2966124587218335,
      "entropy_savings_percent_vs_raw_q8_anchor": 21.29234426597708
    },
    {
      "source_stage": "stage27",
      "sample": "driving",
      "method": "uniform",
      "reference_gap": 16,
      "total_frames": 81,
      "keyframe_count": 6,
      "indices": "0 16 32 48 64 80",
      "quality_adapter_all_psnr": 23.804648425598188,
      "quality_adapter_middle_psnr": 23.118390444544385,
      "primary_anchor_bytes": 2875392,
      "primary_anchor_mib_per_frame": 0.033854166666666664,
      "qparam_bytes": 624,
      "index_bytes": 12,
      "timestamp_bytes": 12,
      "metadata_bytes": 192,
      "container_bytes": 2876232,
      "container_mib_per_frame": 0.03386405662254051,
      "container_overhead_bytes": 840,
      "container_overhead_percent_vs_anchor": 0.02921340811965812,
      "entropy_anchor_bytes": 2263506,
      "entropy_anchor_mib_per_frame": 0.026649969595449942,
      "entropy_container_bytes": 2264346,
      "entropy_container_mib_per_frame": 0.026659859551323786,
      "q8_zero_order_entropy_bits_per_value": 6.29759281517094,
      "entropy_savings_percent_vs_raw_q8_anchor": 21.280089810363247
    },
    {
      "source_stage": "stage27",
      "sample": "driving",
      "method": "anchor_segment_rd",
      "reference_gap": 16,
      "total_frames": 81,
      "keyframe_count": 6,
      "indices": "0 8 16 38 58 80",
      "quality_adapter_all_psnr": 23.517038747768073,
      "quality_adapter_middle_psnr": 22.803915186822096,
      "primary_anchor_bytes": 2875392,
      "primary_anchor_mib_per_frame": 0.033854166666666664,
      "qparam_bytes": 624,
      "index_bytes": 12,
      "timestamp_bytes": 12,
      "metadata_bytes": 192,
      "container_bytes": 2876232,
      "container_mib_per_frame": 0.03386405662254051,
      "container_overhead_bytes": 840,
      "container_overhead_percent_vs_anchor": 0.02921340811965812,
      "entropy_anchor_bytes": 2263511,
      "entropy_anchor_mib_per_frame": 0.026650028464234907,
      "entropy_container_bytes": 2264351,
      "entropy_container_mib_per_frame": 0.026659918420108748,
      "q8_zero_order_entropy_bits_per_value": 6.297606726317664,
      "entropy_savings_percent_vs_raw_q8_anchor": 21.279915921029204
    },
    {
      "source_stage": "stage27",
      "sample": "robot",
      "method": "uniform",
      "reference_gap": 4,
      "total_frames": 77,
      "keyframe_count": 20,
      "indices": "0 4 8 12 16 20 24 28 32 36 40 44 48 52 56 60 64 68 72 76",
      "quality_adapter_all_psnr": 25.19121523230494,
      "quality_adapter_middle_psnr": 22.873993843009693,
      "primary_anchor_bytes": 9584640,
      "primary_anchor_mib_per_frame": 0.11870941558441558,
      "qparam_bytes": 2080,
      "index_bytes": 40,
      "timestamp_bytes": 40,
      "metadata_bytes": 192,
      "container_bytes": 9586992,
      "container_mib_per_frame": 0.11873854599989854,
      "container_overhead_bytes": 2352,
      "container_overhead_percent_vs_anchor": 0.02453926282051282,
      "entropy_anchor_bytes": 7637314,
      "entropy_anchor_mib_per_frame": 0.09459104166402445,
      "entropy_container_bytes": 7639666,
      "entropy_container_mib_per_frame": 0.0946201720795074,
      "q8_zero_order_entropy_bits_per_value": 6.374627737713675,
      "entropy_savings_percent_vs_raw_q8_anchor": 20.31715327857906
    },
    {
      "source_stage": "stage27",
      "sample": "robot",
      "method": "anchor_segment_rd",
      "reference_gap": 4,
      "total_frames": 77,
      "keyframe_count": 20,
      "indices": "0 6 10 14 18 22 24 28 34 38 40 42 44 46 52 56 60 66 74 76",
      "quality_adapter_all_psnr": 25.277672042122344,
      "quality_adapter_middle_psnr": 22.974416447813354,
      "primary_anchor_bytes": 9584640,
      "primary_anchor_mib_per_frame": 0.11870941558441558,
      "qparam_bytes": 2080,
      "index_bytes": 40,
      "timestamp_bytes": 40,
      "metadata_bytes": 192,
      "container_bytes": 9586992,
      "container_mib_per_frame": 0.11873854599989854,
      "container_overhead_bytes": 2352,
      "container_overhead_percent_vs_anchor": 0.02453926282051282,
      "entropy_anchor_bytes": 7637382,
      "entropy_anchor_mib_per_frame": 0.09459188386991427,
      "entropy_container_bytes": 7639734,
      "entropy_container_mib_per_frame": 0.09462101428539722,
      "q8_zero_order_entropy_bits_per_value": 6.374684495192308,
      "entropy_savings_percent_vs_raw_q8_anchor": 20.316443810096153
    },
    {
      "source_stage": "stage27",
      "sample": "robot",
      "method": "uniform",
      "reference_gap": 8,
      "total_frames": 77,
      "keyframe_count": 11,
      "indices": "0 8 16 24 32 40 48 56 64 72 76",
      "quality_adapter_all_psnr": 22.98300789935102,
      "quality_adapter_middle_psnr": 21.51250600039049,
      "primary_anchor_bytes": 5271552,
      "primary_anchor_mib_per_frame": 0.06529017857142858,
      "qparam_bytes": 1144,
      "index_bytes": 22,
      "timestamp_bytes": 22,
      "metadata_bytes": 192,
      "container_bytes": 5272932,
      "container_mib_per_frame": 0.06530727039683949,
      "container_overhead_bytes": 1380,
      "container_overhead_percent_vs_anchor": 0.026178248834498836,
      "entropy_anchor_bytes": 4200969,
      "entropy_anchor_mib_per_frame": 0.052030600510634385,
      "entropy_container_bytes": 4202349,
      "entropy_container_mib_per_frame": 0.0520476923360453,
      "q8_zero_order_entropy_bits_per_value": 6.375305033508159,
      "entropy_savings_percent_vs_raw_q8_anchor": 20.30868708114802
    },
    {
      "source_stage": "stage27",
      "sample": "robot",
      "method": "anchor_segment_rd",
      "reference_gap": 8,
      "total_frames": 77,
      "keyframe_count": 11,
      "indices": "0 10 18 24 28 38 42 46 56 68 76",
      "quality_adapter_all_psnr": 22.571216185720193,
      "quality_adapter_middle_psnr": 21.021777652098482,
      "primary_anchor_bytes": 5271552,
      "primary_anchor_mib_per_frame": 0.06529017857142858,
      "qparam_bytes": 1144,
      "index_bytes": 22,
      "timestamp_bytes": 22,
      "metadata_bytes": 192,
      "container_bytes": 5272932,
      "container_mib_per_frame": 0.06530727039683949,
      "container_overhead_bytes": 1380,
      "container_overhead_percent_vs_anchor": 0.026178248834498836,
      "entropy_anchor_bytes": 4200380,
      "entropy_anchor_mib_per_frame": 0.052023305521382915,
      "entropy_container_bytes": 4201760,
      "entropy_container_mib_per_frame": 0.05204039734679383,
      "q8_zero_order_entropy_bits_per_value": 6.374411179098679,
      "entropy_savings_percent_vs_raw_q8_anchor": 20.319860261266513
    },
    {
      "source_stage": "stage27",
      "sample": "robot",
      "method": "uniform",
      "reference_gap": 16,
      "total_frames": 77,
      "keyframe_count": 6,
      "indices": "0 16 32 48 64 76",
      "quality_adapter_all_psnr": 21.42610490500266,
      "quality_adapter_middle_psnr": 20.554339141994358,
      "primary_anchor_bytes": 2875392,
      "primary_anchor_mib_per_frame": 0.03561282467532467,
      "qparam_bytes": 624,
      "index_bytes": 12,
      "timestamp_bytes": 12,
      "metadata_bytes": 192,
      "container_bytes": 2876232,
      "container_mib_per_frame": 0.03562322839514002,
      "container_overhead_bytes": 840,
      "container_overhead_percent_vs_anchor": 0.02921340811965812,
      "entropy_anchor_bytes": 2291764,
      "entropy_anchor_mib_per_frame": 0.02838436968914874,
      "entropy_container_bytes": 2292604,
      "entropy_container_mib_per_frame": 0.028394773408964083,
      "q8_zero_order_entropy_bits_per_value": 6.376213051994302,
      "entropy_savings_percent_vs_raw_q8_anchor": 20.297336850071225
    },
    {
      "source_stage": "stage27",
      "sample": "robot",
      "method": "anchor_segment_rd",
      "reference_gap": 16,
      "total_frames": 77,
      "keyframe_count": 6,
      "indices": "0 18 28 38 52 76",
      "quality_adapter_all_psnr": 20.567524314710386,
      "quality_adapter_middle_psnr": 19.622336233724408,
      "primary_anchor_bytes": 2875392,
      "primary_anchor_mib_per_frame": 0.03561282467532467,
      "qparam_bytes": 624,
      "index_bytes": 12,
      "timestamp_bytes": 12,
      "metadata_bytes": 192,
      "container_bytes": 2876232,
      "container_mib_per_frame": 0.03562322839514002,
      "container_overhead_bytes": 840,
      "container_overhead_percent_vs_anchor": 0.02921340811965812,
      "entropy_anchor_bytes": 2291104,
      "entropy_anchor_mib_per_frame": 0.02837619533786526,
      "entropy_container_bytes": 2291944,
      "entropy_container_mib_per_frame": 0.028386599057680602,
      "q8_zero_order_entropy_bits_per_value": 6.374376780626781,
      "entropy_savings_percent_vs_raw_q8_anchor": 20.320290242165242
    }
  ],
  "aggregate": {
    "stage26/uniform": {
      "count": 16,
      "mean_primary_anchor_mib_per_frame": 0.11177096015963203,
      "mean_container_mib_per_frame": 0.11179843884697896,
      "mean_entropy_container_mib_per_frame": 0.08875509970880423,
      "mean_overhead_percent_vs_anchor": 0.025846283880480058,
      "mean_entropy_bits_per_value": 6.351033181558638,
      "mean_entropy_savings_percent_vs_raw_q8_anchor": 20.612085230517025
    },
    "stage27/anchor_segment_rd": {
      "count": 12,
      "mean_primary_anchor_mib_per_frame": 0.07190346545815296,
      "mean_container_mib_per_frame": 0.07192195958389348,
      "mean_entropy_container_mib_per_frame": 0.05710426629956228,
      "mean_overhead_percent_vs_anchor": 0.026619792244792242,
      "mean_entropy_bits_per_value": 6.351353170965801,
      "mean_entropy_savings_percent_vs_raw_q8_anchor": 20.608085362927486
    },
    "stage27/uniform": {
      "count": 12,
      "mean_primary_anchor_mib_per_frame": 0.07190346545815296,
      "mean_container_mib_per_frame": 0.07192195958389348,
      "mean_entropy_container_mib_per_frame": 0.05710230238847568,
      "mean_overhead_percent_vs_anchor": 0.026619792244792242,
      "mean_entropy_bits_per_value": 6.351305247366445,
      "mean_entropy_savings_percent_vs_raw_q8_anchor": 20.60868440791943
    }
  }
}